hypersonic_heygen/__init__.py
hypersonic_heygen/hya.py
hypersonic_heygen/assets/LiveAvatar_v2.ipynb
hypersonic_heygen/assets/images/app-key.png
hypersonic_heygen-2.0.6.dist-info/METADATA
hypersonic_heygen-2.0.6.dist-info/WHEEL
hypersonic_heygen-2.0.6.dist-info/entry_points.txt
hypersonic_heygen-2.0.6.dist-info/top_level.txt
hypersonic_heygen-2.0.6.dist-info/RECORD
