Metadata-Version: 2.4
Name: hypersonic-heygen
Version: 2.0.6
Summary: Hypersonic HeyGen v2 — LiveAvatar (WebRTC) teaching & demo toolkit
Author-email: Krish Ambady <ambady1960@hotmail.com>
License-Expression: MIT
Project-URL: Homepage, https://pypi.org/project/hypersonic-heygen/
Requires-Python: >=3.9
Requires-Dist: requests>=2.31.0
